<?xml version="1.0" encoding="UTF-8"?><record_update table="question_choice">
    <question_choice action="INSERT_OR_UPDATE">
        <inactive>false</inactive>
        <order>200</order>
        <published_ref/>
        <question display_value="Employee Name">0771c243836d26101e5de070deaad3ce</question>
        <sys_class_name>question_choice</sys_class_name>
        <sys_created_by>admin</sys_created_by>
        <sys_created_on>2025-05-21 13:01:22</sys_created_on>
        <sys_id>0ce3081783e566101e5de070deaad315</sys_id>
        <sys_mod_count>0</sys_mod_count>
        <sys_name>Carol Coughlin</sys_name>
        <sys_package display_value="LaptopRequest" source="x_1755447_laptop_0">fd80f47683e1e2101e5de070deaad311</sys_package>
        <sys_policy/>
        <sys_scope display_value="LaptopRequest">fd80f47683e1e2101e5de070deaad311</sys_scope>
        <sys_update_name>question_choice_0ce3081783e566101e5de070deaad315</sys_update_name>
        <sys_updated_by>admin</sys_updated_by>
        <sys_updated_on>2025-05-21 13:01:22</sys_updated_on>
        <text>Carol Coughlin</text>
        <value>carol_coughlin</value>
    </question_choice>
    <fx_price action="delete_multiple" query="id=0ce3081783e566101e5de070deaad315"/>
</record_update>
